escp/__init__.py
escp/commands/__init__.py
escp/commands/commands.py
escp/commands/commands_24_48_pin.py
escp/commands/commands_9_pin.py
escp/commands/exceptions.py
escp/commands/lookup.py
escp/commands/magic_encoding.py
escp/commands/parameters.py
escp/demo/__init__.py
escp/demo/char_tables.py
escp/demo/common.py
escp/demo/demo.py
escp/demo/i18n_char_set.py
escp/demo/poem.py
escp/demo/test_page.py
escp/printer/__init__.py
escp/printer/debug_printer.py
escp/printer/exceptions.py
escp/printer/output_printer.py
escp/printer/printer.py
escp/printer/usb_printer.py
escp-0.0.6.dist-info/LICENSE
escp-0.0.6.dist-info/METADATA
escp-0.0.6.dist-info/WHEEL
escp-0.0.6.dist-info/top_level.txt
escp-0.0.6.dist-info/RECORD
