Metadata-Version: 2.1
Name: escp
Version: 0.0.6
Summary: A library to drive ESC/P printers
Home-page: https://github.com/yackx/python-escp
Author: Youri Ackx
License: GPL
Project-URL: Bug Tracker, https://github.com/yackx/python-escp/issues
Project-URL: Documentation, https://github.com/yackx/python-escp/blob/master/README.md
Project-URL: Release Notes, https://github.com/yackx/python-escp/releases
Keywords: ESC/P,printers,printing,dot matrix
Classifier: Development Status :: 3 - Alpha
Classifier: Environment :: Console
Classifier: Intended Audience :: Developers
Classifier: License :: OSI Approved :: GNU General Public License v3 or later (GPLv3+)
Classifier: Operating System :: OS Independent
Classifier: Programming Language :: Python
Classifier: Programming Language :: Python :: 3
Classifier: Programming Language :: Python :: Implementation :: CPython
Classifier: Topic :: Software Development :: Libraries :: Python Modules
Classifier: Topic :: System :: Hardware :: Universal Serial Bus (USB) :: Printer
Requires-Python: >=3.11
License-File: LICENSE
Requires-Dist: pyusb (>=1.0.0)
Requires-Dist: setuptools
